reahl/postgresqlsupport.py
reahl_postgresqlsupport-7.0.3.dist-info/LICENSE
reahl_postgresqlsupport-7.0.3.dist-info/METADATA
reahl_postgresqlsupport-7.0.3.dist-info/WHEEL
reahl_postgresqlsupport-7.0.3.dist-info/entry_points.txt
reahl_postgresqlsupport-7.0.3.dist-info/reahl-component.toml
reahl_postgresqlsupport-7.0.3.dist-info/top_level.txt
reahl_postgresqlsupport-7.0.3.dist-info/RECORD
